features_extraction/__init__.py
features_extraction/config/__init__.py
features_extraction/config/config.py
features_extraction/config.py
features_extraction/main.py
features_extraction/malware_dataset/__init__.py
features_extraction/malware_dataset/malware_dataset.py
features_extraction/static/__init__.py
features_extraction/static/extract_features_from_top.py
features_extraction/static/generics.py
features_extraction/static/headers.py
features_extraction/static/imports.py
features_extraction/static/ngrams.py
features_extraction/static/opcodes.py
features_extraction/static/sections.py
features_extraction/static/static_feature_extractor.py
features_extraction/static/strings.py
features_extraction/static/top_features/__init__.py
features_extraction/static/top_features/top_feature_extractor.py
features_extraction/static/top_features/top_features_extractor.py
features_extraction/static/top_features/top_imports.py
features_extraction/static/top_features/top_ngrams.py
features_extraction/static/top_features/top_opcodes.py
features_extraction/static/top_features/top_strings.py
features_extraction/utils.py
dts_cdd_wdis-1.4.2.dist-info/LICENSE
dts_cdd_wdis-1.4.2.dist-info/METADATA
dts_cdd_wdis-1.4.2.dist-info/WHEEL
dts_cdd_wdis-1.4.2.dist-info/RECORD
