Metadata-Version: 2.3
Name: DTS-CDD__Wdis
Version: 1.4.2
Summary: Static Features Extraction Engine
Author: Luca Fabri
Author-email: luca.fabri1999@gmail.com
Requires-Python: >=3.10,<4.0
Classifier: Programming Language :: Python :: 3
Classifier: Programming Language :: Python :: 3.10
Classifier: Programming Language :: Python :: 3.11
Classifier: Programming Language :: Python :: 3.12
Classifier: Programming Language :: Python :: 3.13
Requires-Dist: capstone (>=5.0.1,<5.1.0)
Requires-Dist: info-gain (==1.0.1)
Requires-Dist: ipython (>=8.36.0,<8.37.0)
Requires-Dist: matplotlib (==3.10.3)
Requires-Dist: nltk (>=3.8.1,<3.9.0)
Requires-Dist: notebook (==7.2.2)
Requires-Dist: numpy (==2.2.6)
Requires-Dist: p_tqdm (==1.4.2)
Requires-Dist: pandas (==2.2.3)
Requires-Dist: pefile (>=2024.8.0,<2024.9.0)
Requires-Dist: pyarrow (>=20.0.0,<21.0.0)
Requires-Dist: ruff (>=0.11.6,<0.12.0)
Requires-Dist: scikit-learn (==1.5.0)
Requires-Dist: scipy (>=1.15.0,<1.16.0)
Requires-Dist: seaborn (==0.13.2)
Requires-Dist: setuptools (>=70.0.0,<70.1.0)
Requires-Dist: tqdm (>=4.67.0,<4.68.0)
